test_numpy_setuptools/__init__.py
test_numpy_setuptools/test_numpy_setuptools_main.py
test_numpy_setuptools/test_numpy_setuptools_multi.py
test_numpy_setuptools-1.4.dist-info/METADATA
test_numpy_setuptools-1.4.dist-info/WHEEL
test_numpy_setuptools-1.4.dist-info/top_level.txt
test_numpy_setuptools-1.4.dist-info/RECORD
