Metadata-Version: 2.1
Name: test-numpy-setuptools
Version: 1.4
Summary: test_numpy_setuptools backpack
Home-page: UNKNOWN
Author: smilencezq
Author-email: smilencezq@163.com
License: UNKNOWN
Platform: UNKNOWN
Requires: numpy
